arcade_zoho_creator_api/__init__.py
arcade_zoho_creator_api/tools/__init__.py
arcade_zoho_creator_api/tools/request_body_schemas.py
arcade_zoho_creator_api/wrapper_tools/AddRecordsToZohoForm.json
arcade_zoho_creator_api/wrapper_tools/CreateBulkReadJob.json
arcade_zoho_creator_api/wrapper_tools/DeleteReportRecords.json
arcade_zoho_creator_api/wrapper_tools/DeleteZohoRecord.json
arcade_zoho_creator_api/wrapper_tools/DownloadBulkReadJobCsv.json
arcade_zoho_creator_api/wrapper_tools/DownloadFileFromRecord.json
arcade_zoho_creator_api/wrapper_tools/DownloadZohoFile.json
arcade_zoho_creator_api/wrapper_tools/FetchRecordDetail.json
arcade_zoho_creator_api/wrapper_tools/FetchWorkspaceAppMeta.json
arcade_zoho_creator_api/wrapper_tools/FetchZohoAppSections.json
arcade_zoho_creator_api/wrapper_tools/FetchZohoCreatorPagesMeta.json
arcade_zoho_creator_api/wrapper_tools/FetchZohoFormFieldsMetadata.json
arcade_zoho_creator_api/wrapper_tools/FetchZohoFormMetaInformation.json
arcade_zoho_creator_api/wrapper_tools/FetchZohoRecordDetail.json
arcade_zoho_creator_api/wrapper_tools/FetchZohoRecords.json
arcade_zoho_creator_api/wrapper_tools/FetchZohoReportRecords.json
arcade_zoho_creator_api/wrapper_tools/FetchZohoReportsMeta.json
arcade_zoho_creator_api/wrapper_tools/GetApplicationMetaInfo.json
arcade_zoho_creator_api/wrapper_tools/GetBulkReadJobDetails.json
arcade_zoho_creator_api/wrapper_tools/InsertRecordsInZohoForm.json
arcade_zoho_creator_api/wrapper_tools/UpdateZohoCreatorReportRecords.json
arcade_zoho_creator_api/wrapper_tools/UpdateZohoRecord.json
arcade_zoho_creator_api-1.0.0.dist-info/METADATA
arcade_zoho_creator_api-1.0.0.dist-info/WHEEL
arcade_zoho_creator_api-1.0.0.dist-info/entry_points.txt
arcade_zoho_creator_api-1.0.0.dist-info/licenses/LICENSE
arcade_zoho_creator_api-1.0.0.dist-info/RECORD
